{
  "project_info": {
    "project_number": "1084599954475",
    "project_id": "taa1-bbc3c",
    "storage_bucket": "taa1-bbc3c.appspot.com"
  },
  "client": [
    {
      "client_info": {
        "mobilesdk_app_id": "1:1084599954475:android:9aa003eed81d36456b4e6e",
        "android_client_info": {
          "package_name": "com.example.profile"
        }
      },
      "oauth_client": [
        {
          "client_id": "1084599954475-q19l42bmss7tg1sjuareghp85nfajrbc.apps.googleusercontent.com",
          "client_type": 3
        }
      ],
      "api_key": [
        {
          "current_key": "AIzaSyB6R8MvB2C5HPbkaJ73clbT2akOxzPeYyQ"
        }
      ],
      "services": {
        "appinvite_service": {
          "other_platform_oauth_client": [
            {
              "client_id": "1084599954475-q19l42bmss7tg1sjuareghp85nfajrbc.apps.googleusercontent.com",
              "client_type": 3
            }
          ]
        }
      }
    }
  ],
  "configuration_version": "1"
}